canopy/__init__.py
canopy/static/canopy.js
canopy/static/canopy.js.LICENSE.txt
canopy/templates/__init__.py
canopy/templates/about.html
canopy/templates/archive/year.html
canopy/templates/chat.html
canopy/templates/colorama.html
canopy/templates/entry.html
canopy/templates/home.html
canopy/templates/icon_editor.html
canopy/templates/new.html
canopy/templates/now.html
canopy/templates/recent.html
canopy/templates/room.html
canopy/templates/settings.html
canopy/templates/sign_in.html
canopy/templates/template.html
canopy/templates/welcome.html
canopy_network-0.0.52.dist-info/entry_points.txt
canopy_network-0.0.52.dist-info/LICENSE
canopy_network-0.0.52.dist-info/WHEEL
canopy_network-0.0.52.dist-info/METADATA
canopy_network-0.0.52.dist-info/RECORD
