Metadata-Version: 2.1
Name: canopy-network
Version: 0.0.52
Summary: A decentralized social network of personal websites
Home-page: https://understory.cloud/canopy.git
License: AGPL-3.0-or-later
Author: Angelo Gladding
Author-email: angelo@lahacker.net
Requires-Python: >=3.9,<3.10
Classifier: License :: OSI Approved :: GNU Affero General Public License v3 or later (AGPLv3+)
Classifier: Programming Language :: Python :: 3
Classifier: Programming Language :: Python :: 3.9
Requires-Dist: understory (>=0.0.63,<0.0.64)
Project-URL: Homepage, https://canopy.stream
Project-URL: Issues, https://github.com/canopy/canopy/issues
Project-URL: Repository, https://understory.cloud/canopy.git
